dmfo/__init__.py
dmfo/__main__.py
dmfo/classes/__init__.py
dmfo/classes/vcsfiledata.py
dmfo/constants/__init__.py
dmfo/constants/mso/__init__.py
dmfo/constants/mso/mso.py
dmfo/constants/mso/pp.py
dmfo/constants/mso/wd.py
dmfo/driver/__init__.py
dmfo/driver/common.py
dmfo/driver/differ/__init__.py
dmfo/driver/differ/pp.py
dmfo/driver/differ/wd.py
dmfo/driver/merger/__init__.py
dmfo/driver/merger/wd.py
dmfo/files/__init__.py
dmfo/installer/__init__.py
DMFO-0.1.0.dist-info/LICENSE
DMFO-0.1.0.dist-info/METADATA
DMFO-0.1.0.dist-info/WHEEL
DMFO-0.1.0.dist-info/entry_points.txt
DMFO-0.1.0.dist-info/top_level.txt
DMFO-0.1.0.dist-info/RECORD
