Metadata-Version: 2.1
Name: DMFO
Version: 0.1.0
Summary: Diff and Merge For Office
Home-page: https://github.com/lcnittl/DMFO
Author: Christian Knittl-Frank
Author-email: lcnittl@gmail.com
License: GPL-3.0
Download-URL: http://pypi.python.org/pypi/DMFO
Project-URL: GitHub: repo, https://github.com/lcnittl/DMFO
Project-URL: GitHub: issues, https://github.com/lcnittl/DMFO/issues
Platform: UNKNOWN
Classifier: Development Status :: 3 - Alpha
Classifier: Environment :: Console
Classifier: Intended Audience :: Developers
Classifier: License :: OSI Approved :: GNU General Public License v3 (GPLv3)
Classifier: License :: OSI Approved :: GNU General Public License v3 or later (GPLv3+)
Classifier: Operating System :: POSIX :: Linux
Classifier: Programming Language :: Python :: 3
Classifier: Programming Language :: Python :: 3 :: Only
Classifier: Programming Language :: Python :: 3.8
Classifier: Programming Language :: Python :: 3.9
Classifier: Topic :: Utilities
Requires-Python: >=3.8
Requires-Dist: colorlog (>=4.1.0)
Requires-Dist: pywin32 (>=228)
